metabodirect/__init__.py
metabodirect/__main__.py
metabodirect/create_networks.py
metabodirect/diagnostics.py
metabodirect/get_args.py
metabodirect/preprocessing.py
metabodirect/r_control.py
metabodirect/spans.R
metabodirect/test_normalization.py
metabodirect/transformations.py
metabodirect/R_scripts_templates/KEGG_annotation_template.R
metabodirect/R_scripts_templates/SPANS_score_template.R
metabodirect/R_scripts_templates/custom_functions.R
metabodirect/R_scripts_templates/data_chemodiversity_template.R
metabodirect/R_scripts_templates/data_exploration_template.R
metabodirect/R_scripts_templates/data_exploration_template_2_groups.R
metabodirect/R_scripts_templates/data_statistics_template.R
metabodirect/R_scripts_templates/data_statistics_template_2_groups.R
metabodirect/R_scripts_templates/network_stats_template.R
metabodirect/data/Report.csv
metabodirect/data/compound_class_table.csv
metabodirect/data/metadata.csv
metabodirect/data/transf_key.csv
metabodirect-1.0.10.dist-info/licenses/LICENSE
metabodirect-1.0.10.dist-info/METADATA
metabodirect-1.0.10.dist-info/WHEEL
metabodirect-1.0.10.dist-info/entry_points.txt
metabodirect-1.0.10.dist-info/top_level.txt
metabodirect-1.0.10.dist-info/RECORD
