Metadata-Version: 2.4
Name: metabodirect
Version: 1.0.10
Summary: Analyze FT-ICR-MS data
Home-page: https://github.com/Coayala/MetaboDirect
Author: Christian Ayala
Author-email: cayalaortiz@email.arizona.edu
License: LICENSE
Classifier: License :: OSI Approved :: MIT License
Classifier: Programming Language :: Python :: 3
Classifier: Programming Language :: Python :: 3.11
License-File: LICENSE
Requires-Dist: pandas
Requires-Dist: numpy
Requires-Dist: py4cytoscape
Requires-Dist: seaborn
Requires-Dist: more-itertools
Requires-Dist: argparse
Requires-Dist: statsmodels
Requires-Dist: loguru
Dynamic: author
Dynamic: author-email
Dynamic: classifier
Dynamic: description
Dynamic: description-content-type
Dynamic: home-page
Dynamic: license
Dynamic: license-file
Dynamic: requires-dist
Dynamic: summary
